LICENSE
MANIFEST.in
README.md
requirements.txt
setup.py
terodata/__init__.py
terodata/client.py
terodata/version.py
terodata.egg-info/PKG-INFO
terodata.egg-info/SOURCES.txt
terodata.egg-info/dependency_links.txt
terodata.egg-info/requires.txt
terodata.egg-info/top_level.txt
tests/__init__.py
tests/test_client.py
tests/test_version.py