Metadata-Version: 2.1
Name: terodata
Version: 1.1.0
Summary: Python binding for tero-data
Home-page: https://github.com/isardsat/tero-data
Author: Lobelia Earth
Author-email: info@lobelia.earth
License: UNKNOWN
Platform: UNKNOWN
